irclog2html/__init__.py
irclog2html/__main__.py
irclog2html/_version.py
irclog2html/irclog.css
irclog2html/irclog2html.py
irclog2html/irclogsearch.py
irclog2html/irclogserver.py
irclog2html/logs2html.py
irclog2html/xchatlogsplit.py
irclog2html-4.1.0.dist-info/licenses/COPYING
irclog2html-4.1.0.dist-info/METADATA
irclog2html-4.1.0.dist-info/WHEEL
irclog2html-4.1.0.dist-info/entry_points.txt
irclog2html-4.1.0.dist-info/top_level.txt
irclog2html-4.1.0.dist-info/RECORD
