Metadata-Version: 2.4
Name: irclog2html
Version: 4.1.0
Summary: Convert IRC logs to HTML
Home-page: https://mg.pov.lt/irclog2html/
Author: Marius Gedminas
Author-email: marius@gedmin.as
License: GPL-3.0-or-later
Keywords: irc log colorizer html wsgi
Platform: any
Classifier: Development Status :: 4 - Beta
Classifier: Intended Audience :: System Administrators
Classifier: Operating System :: OS Independent
Classifier: Programming Language :: Python :: 3.10
Classifier: Programming Language :: Python :: 3.11
Classifier: Programming Language :: Python :: 3.12
Classifier: Programming Language :: Python :: 3.13
Classifier: Programming Language :: Python :: 3.14
Classifier: Programming Language :: Python :: Implementation :: CPython
Classifier: Programming Language :: Python :: Implementation :: PyPy
Requires-Python: >=3.10
License-File: COPYING
Provides-Extra: test
Requires-Dist: zope.testing; extra == "test"
Dynamic: author
Dynamic: author-email
Dynamic: classifier
Dynamic: description
Dynamic: description-content-type
Dynamic: home-page
Dynamic: keywords
Dynamic: license
Dynamic: license-file
Dynamic: platform
Dynamic: provides-extra
Dynamic: requires-python
Dynamic: summary
